roguewave/__init__.py
roguewave/log.py
roguewave/colocate/__init__.py
roguewave/colocate/bulk.py
roguewave/colocate/pointdata.py
roguewave/colocate/spectra.py
roguewave/filecache/__init__.py
roguewave/filecache/cache_object.py
roguewave/filecache/exceptions.py
roguewave/filecache/filecache.py
roguewave/filecache/remote_resources.py
roguewave/interpolate/__init__.py
roguewave/interpolate/cluster.py
roguewave/interpolate/dataarray.py
roguewave/interpolate/dataframe.py
roguewave/interpolate/dataset.py
roguewave/interpolate/general.py
roguewave/interpolate/geometry.py
roguewave/interpolate/nd_interp.py
roguewave/interpolate/points.py
roguewave/interpolate/spline.py
roguewave/io/__init__.py
roguewave/io/io.py
roguewave/modeldata/__init__.py
roguewave/modeldata/extract.py
roguewave/modeldata/keygeneration.py
roguewave/modeldata/modelinformation.py
roguewave/modeldata/open_remote.py
roguewave/modeldata/open_remote_restart_files.py
roguewave/modeldata/sofarspectralapi.py
roguewave/modeldata/timebase.py
roguewave/observations/__init__.py
roguewave/observations/satellite.py
roguewave/spotter/__init__.py
roguewave/spotter/_pressure_analysis.py
roguewave/spotter/analysis.py
roguewave/spotter/parser.py
roguewave/spotter/read_csv_data.py
roguewave/spotter/file_formats/BARO.json
roguewave/spotter/file_formats/BARO_RAW.json
roguewave/spotter/file_formats/FLT.json
roguewave/spotter/file_formats/GMN.json
roguewave/spotter/file_formats/GPS.json
roguewave/spotter/file_formats/LOC.json
roguewave/spotter/file_formats/RAINDB.json
roguewave/spotter/file_formats/RBRD.json
roguewave/spotter/file_formats/RBRDT.json
roguewave/spotter/file_formats/SMD-RBR.json
roguewave/spotter/file_formats/SMD-RBRD.json
roguewave/spotter/file_formats/SMD-RBRDT.json
roguewave/spotter/file_formats/SPC.json
roguewave/spotter/file_formats/SST.json
roguewave/spotter/file_formats/TIME.json
roguewave/spotter/file_formats/__init__.py
roguewave/spotter/file_formats/_create_formats.py
roguewave-0.2.31.dist-info/LICENSE
roguewave-0.2.31.dist-info/METADATA
roguewave-0.2.31.dist-info/WHEEL
roguewave-0.2.31.dist-info/top_level.txt
roguewave-0.2.31.dist-info/RECORD
