Metadata-Version: 2.1
Name: roguewave
Version: 0.2.31
Summary: Python package to interact with Sofar wave data
Home-page: https://github.com/sofarocean/roguewave.git
Author: Pieter Bart Smit
Author-email: sofaroceangithubbot@gmail.com
License: Apache 2 License
Project-URL: Sofar Ocean Site, https://www.sofarocean.com
Classifier: Programming Language :: Python :: 3
Classifier: Programming Language :: Python :: 3.9
Classifier: License :: OSI Approved :: Apache Software License
Classifier: Operating System :: OS Independent
License-File: LICENSE
Requires-Dist: pysofar (>=0.1.13)
Requires-Dist: numpy
Requires-Dist: netCDF4
Requires-Dist: pandas
Requires-Dist: scipy
Requires-Dist: numba
Requires-Dist: tqdm
Requires-Dist: h5netcdf
Requires-Dist: boto3
Requires-Dist: xarray
Requires-Dist: requests
Requires-Dist: numba-progress
Requires-Dist: linearwavetheory
Requires-Dist: roguewavespectrum
Provides-Extra: full
Requires-Dist: qpsolvers ; extra == 'full'
Requires-Dist: cvxopt ; extra == 'full'
Requires-Dist: pygrib ; extra == 'full'
Provides-Extra: grib
Requires-Dist: pygrib ; extra == 'grib'
Provides-Extra: optimization
Requires-Dist: cvxopt ; extra == 'optimization'
Requires-Dist: pygrib ; extra == 'optimization'
